noir/__init__.py
noir/engine.py
noir_game_engine-0.1.1.dist-info/LICENSE
noir_game_engine-0.1.1.dist-info/METADATA
noir_game_engine-0.1.1.dist-info/WHEEL
noir_game_engine-0.1.1.dist-info/top_level.txt
noir_game_engine-0.1.1.dist-info/RECORD
