Metadata-Version: 2.1
Name: noir_game_engine
Version: 0.1.1
Summary: A simple text adventure game engine for beginners.
Home-page: https://github.com/AndrewAMur/Noir
Author: Andrew AMur
Author-email: your_email@example.com
Classifier: Programming Language :: Python :: 3
Classifier: License :: OSI Approved :: MIT License
Classifier: Operating System :: OS Independent
Requires-Python: >=3.6
License-File: LICENSE
